{
  "project_info": {
    "project_number": "140397440960",
    "firebase_url": "https://tfg-firebase.firebaseio.com",
    "project_id": "tfg-firebase",
    "storage_bucket": "tfg-firebase.appspot.com"
  },
  "client": [
    {
      "client_info": {
        "mobilesdk_app_id": "1:140397440960:android:dd5e174ddf0de52c",
        "android_client_info": {
          "package_name": "TFG.Droid"
        }
      },
      "oauth_client": [
        {
          "client_id": "140397440960-5i94e1l0jh92ck7u44oli931dc3csdib.apps.googleusercontent.com",
          "client_type": 1,
          "android_info": {
            "package_name": "TFG.Droid",
            "certificate_hash": "ee4127035abeccae299344194f307886ba7beba1"
          }
        },
        {
          "client_id": "140397440960-llo4lvofq7ksdd6mk2igdmebag159tai.apps.googleusercontent.com",
          "client_type": 3
        }
      ],
      "api_key": [
        {
          "current_key": "AIzaSyAI9WMR4yk79hymi_dbsXhw-Oz3C99lv4k"
        }
      ],
      "services": {
        "analytics_service": {
          "status": 1
        },
        "appinvite_service": {
          "status": 2,
          "other_platform_oauth_client": [
            {
              "client_id": "140397440960-llo4lvofq7ksdd6mk2igdmebag159tai.apps.googleusercontent.com",
              "client_type": 3
            }
          ]
        },
        "ads_service": {
          "status": 2
        }
      }
    }
  ],
  "configuration_version": "1"
}